scicat_sdk_py/__init__.py
scicat_sdk_py/api_client.py
scicat_sdk_py/api_response.py
scicat_sdk_py/configuration.py
scicat_sdk_py/exceptions.py
scicat_sdk_py/py.typed
scicat_sdk_py/rest.py
scicat_sdk_py/api/__init__.py
scicat_sdk_py/api/admin_api.py
scicat_sdk_py/api/attachments_v4_api.py
scicat_sdk_py/api/auth_api.py
scicat_sdk_py/api/datablocks_api.py
scicat_sdk_py/api/datasets_api.py
scicat_sdk_py/api/datasets_public_v4_api.py
scicat_sdk_py/api/datasets_v4_api.py
scicat_sdk_py/api/elastic_search_api.py
scicat_sdk_py/api/health_api.py
scicat_sdk_py/api/history_api.py
scicat_sdk_py/api/instruments_api.py
scicat_sdk_py/api/jobs_api.py
scicat_sdk_py/api/jobs_v4_api.py
scicat_sdk_py/api/logbooks_api.py
scicat_sdk_py/api/origdatablocks_api.py
scicat_sdk_py/api/origdatablocks_public_v4_api.py
scicat_sdk_py/api/origdatablocks_v4_api.py
scicat_sdk_py/api/policies_api.py
scicat_sdk_py/api/proposals_api.py
scicat_sdk_py/api/published_data_api.py
scicat_sdk_py/api/published_data_v4_api.py
scicat_sdk_py/api/runtime_configurations_api.py
scicat_sdk_py/api/samples_api.py
scicat_sdk_py/api/user_identities_api.py
scicat_sdk_py/api/users_api.py
scicat_sdk_py/models/__init__.py
scicat_sdk_py/models/admin_update_user_password_dto.py
scicat_sdk_py/models/attachment.py
scicat_sdk_py/models/attachment_relationship_class.py
scicat_sdk_py/models/attachment_relationships_v4_dto.py
scicat_sdk_py/models/count_api_response.py
scicat_sdk_py/models/create_attachment_v3_dto.py
scicat_sdk_py/models/create_attachment_v4_dto.py
scicat_sdk_py/models/create_custom_jwt.py
scicat_sdk_py/models/create_datablock_dto.py
scicat_sdk_py/models/create_dataset_datablock_dto.py
scicat_sdk_py/models/create_dataset_dto.py
scicat_sdk_py/models/create_dataset_orig_datablock_dto.py
scicat_sdk_py/models/create_derived_dataset_obsolete_dto.py
scicat_sdk_py/models/create_instrument_dto.py
scicat_sdk_py/models/create_job_dto.py
scicat_sdk_py/models/create_job_dto_v3.py
scicat_sdk_py-4.27.0.dist-info/METADATA
scicat_sdk_py-4.27.0.dist-info/WHEEL
scicat_sdk_py-4.27.0.dist-info/top_level.txt
scicat_sdk_py-4.27.0.dist-info/RECORD
